TempBox/__init__.py
TempBox/core.py
tests/__init__.py
tests/test_core.py
TempBox-0.1.0.dist-info/LICENSE
TempBox-0.1.0.dist-info/METADATA
TempBox-0.1.0.dist-info/WHEEL
TempBox-0.1.0.dist-info/top_level.txt
TempBox-0.1.0.dist-info/RECORD
